pytest_latin_hypercube/__init__.py
pytest_latin_hypercube/latin_hypercube.py
pytest_latin_hypercube-1.0.1.dist-info/METADATA
pytest_latin_hypercube-1.0.1.dist-info/WHEEL
pytest_latin_hypercube-1.0.1.dist-info/licenses/LICENSE
pytest_latin_hypercube-1.0.1.dist-info/RECORD
