Metadata-Version: 2.4
Name: pytest-latin-hypercube
Version: 1.0.1
Summary: Implementation of Latin Hypercube Sampling for pytest.
Project-URL: Documentation, https://pytest-latin-hypercube.github.io
Author-email: Shuaib Ahmed <shuaib2001.sa@gmail.com>
License-Expression: MIT
License-File: LICENSE
Requires-Dist: numpy
Requires-Dist: pytest
Provides-Extra: doc
Requires-Dist: sphinx; extra == 'doc'
Requires-Dist: sphinx-autobuild; extra == 'doc'
Requires-Dist: sphinx-design; extra == 'doc'
Requires-Dist: sphinx-rtd-theme; extra == 'doc'
Requires-Dist: sphinxcontrib-bibtex; extra == 'doc'
Requires-Dist: sphinxcontrib-proof; extra == 'doc'
